aopi_python/__init__.py
aopi_python/ctx.py
aopi_python/index_functions.py
aopi_python/main.py
aopi_python/models/__init__.py
aopi_python/models/dist_info.py
aopi_python/models/package_version.py
aopi_python/models/pythonpackage.py
aopi_python/roles.py
aopi_python/routes/__init__.py
aopi_python/routes/file_router.py
aopi_python/routes/simple/__init__.py
aopi_python/routes/simple/dependencies.py
aopi_python/routes/simple/logic.py
aopi_python/routes/simple/routes.py
aopi_python/templates/simple/index.jinja2
aopi_python/templates/simple/package_versions.jinja2
aopi_python/utils/__init__.py
aopi_python/utils/pydantic_form.py
aopi_python-0.1.30.dist-info/entry_points.txt
aopi_python-0.1.30.dist-info/WHEEL
aopi_python-0.1.30.dist-info/METADATA
aopi_python-0.1.30.dist-info/RECORD
